coiny/__init__.py
coiny/core.py
coiny/utils.py
coiny/tools/checkaccounts.py
coiny-0.0.2.data/scripts/checkaccounts.py
coiny-0.0.2.dist-info/LICENSE
coiny-0.0.2.dist-info/METADATA
coiny-0.0.2.dist-info/WHEEL
coiny-0.0.2.dist-info/entry_points.txt
coiny-0.0.2.dist-info/top_level.txt
coiny-0.0.2.dist-info/RECORD
